{
    "/js/ace.js": "/js/ace.js?id=6fb80185188e6b6159dc",
    "/js/activity.js": "/js/activity.js?id=e11c3deb398f5345bfa4",
    "/js/app.js": "/js/app.js?id=dd4d1f653aa64e584b3c",
    "/css/app.css": "/css/app.css?id=e476b441b8b8467f2bc1",
    "/css/appdark.css": "/css/appdark.css?id=a96c2d6b0a37e6caa91b",
    "/css/landing.css": "/css/landing.css?id=556e926e2e30dfd4135d",
    "/css/quill.css": "/css/quill.css?id=6de568ce294cd0fb8fde",
    "/js/collectioncompose.js": "/js/collectioncompose.js?id=1745a3dbb128da69a805",
    "/js/collections.js": "/js/collections.js?id=85ae5e47c5708ac53638",
    "/js/components.js": "/js/components.js?id=e06ff5005f18ee7349d1",
    "/js/compose.js": "/js/compose.js?id=2a83c322e609512617f2",
    "/js/compose-classic.js": "/js/compose-classic.js?id=c77be3d6940d38401815",
    "/js/developers.js": "/js/developers.js?id=e9bd392f3905126750e8",
    "/js/discover.js": "/js/discover.js?id=931da6e0aa0b96d3bae2",
    "/js/hashtag.js": "/js/hashtag.js?id=d32950a912260896d843",
    "/js/loops.js": "/js/loops.js?id=932b2bc647eea03e2d00",
    "/js/manifest.js": "/js/manifest.js?id=41f053ba9a94d81b39f8",
    "/js/mode-dot.js": "/js/mode-dot.js?id=12af786802405ae9bf0a",
    "/js/profile.js": "/js/profile.js?id=6e47f0af7f445c1a853e",
    "/js/quill.js": "/js/quill.js?id=aa4eb387b80b80807ca0",
    "/js/search.js": "/js/search.js?id=22105a64c589f60ea3d8",
    "/js/status.js": "/js/status.js?id=b9b5cc5f2beaef4cc9af",
    "/js/theme-monokai.js": "/js/theme-monokai.js?id=0046c970e8872f667576",
    "/js/timeline.js": "/js/timeline.js?id=43628a728552ab2c58f4",
    "/js/vendor.js": "/js/vendor.js?id=3c89979756a5ee1af562"
}
